django_content_safe_uploader/migrations/__init__.py
django_content_safe_uploader_demo/__init__.py
django_content_safe_uploader_demo/settings.py
django_content_safe_uploader_demo/urls.py
django_content_safe_uploader_demo/wsgi.py
django_content_safe_uploader-0.1.0.dist-info/LICENSE
django_content_safe_uploader-0.1.0.dist-info/METADATA
django_content_safe_uploader-0.1.0.dist-info/WHEEL
django_content_safe_uploader-0.1.0.dist-info/top_level.txt
django_content_safe_uploader-0.1.0.dist-info/RECORD
