Metadata-Version: 2.1
Name: django-content-safe-uploader
Version: 0.1.0
Summary: FileField security validators: FileExtensionValidator, FileContentMatchesWithFileExtensionValidator.
Author: zencore
Author-email: dobetter@zencore.cn
License: MIT
Keywords: django,django admin,django filefield,libmagic,puremagic,file command
Classifier: Development Status :: 5 - Production/Stable
Classifier: Intended Audience :: Developers
Classifier: Topic :: Software Development :: Libraries :: Python Modules
Classifier: License :: OSI Approved :: MIT License
Classifier: Programming Language :: Python :: 3
Classifier: Programming Language :: Python :: 3 :: Only
License-File: LICENSE
Requires-Dist: django
Requires-Dist: simplemagic (>=0.1.9)
